cpypp/__init__.py
cpypp/__main__.py
cpypp/_cpypp.py
cpypp/_exceptions.py
cpypp/tests/__init__.py
cpypp/tests/copyright.txt
cpypp/tests/py2andpy3.py
cpypp/tests/test_helloworld.py
cpypp/tests/test_import1.py
cpypp/tests/test_import2.py
cpypp/tests/test_print.py
cpypp/tests/test_script01.py
cpypp/tests/test_script02.py
cpypp/tests/test_script03.py
cpypp/tests/test_script04.py
cpypp/tests/imports/__init__.py
cpypp/tests/imports/functions.py
cpypp/tests/imports/import1.py
cpypp/tests/imports/import2.py
cpypp/tests/imports/import3.py
cpypp/tests/imports/import4.py
cpypp/tests/imports/import5.py
cpypp/tests/imports/import6.py
cpypp-1.1.0.data/scripts/cpypp2
cpypp-1.1.0.data/scripts/cpypp3
cpypp-1.1.0.dist-info/LICENSE.md
cpypp-1.1.0.dist-info/METADATA
cpypp-1.1.0.dist-info/WHEEL
cpypp-1.1.0.dist-info/entry_points.txt
cpypp-1.1.0.dist-info/top_level.txt
cpypp-1.1.0.dist-info/RECORD
